AUTHORS
CHANGELOG
CONTRIBUTING.rst
INSTALL
LICENSE
MANIFEST.in
README.rst
VERSION
setup.cfg
setup.py
xal/__init__.py
xal/api.py
xal/provider.py
xal/registry.py
xal/resource.py
xal.egg-info/PKG-INFO
xal.egg-info/SOURCES.txt
xal.egg-info/dependency_links.txt
xal.egg-info/not-zip-safe
xal.egg-info/pbr.json
xal.egg-info/requires.txt
xal.egg-info/top_level.txt
xal/client/__init__.py
xal/client/fabric.py
xal/client/local.py
xal/client/provider.py
xal/dir/__init__.py
xal/dir/generic.py
xal/dir/local.py
xal/dir/provider.py
xal/dir/resource.py
xal/path/__init__.py
xal/path/fabric.py
xal/path/local.py
xal/path/provider.py
xal/path/resource.py
xal/session/__init__.py
xal/session/fabric.py
xal/session/local.py
xal/sh/__init__.py
xal/sh/fabric.py
xal/sh/local.py
xal/sh/provider.py
xal/sh/resource.py
xal/sys/__init__.py
xal/sys/fabric.py
xal/sys/local.py
xal/sys/provider.py
xal/user/__init__.py
xal/user/local.py
xal/user/provider.py
xal/user/resource.py