Metadata-Version: 1.1
Name: xal
Version: 0.3
Summary: Execution abstraction layer for high-level system scripts.
Home-page: https://xal.readthedocs.org/
Author: Benoît Bryon
Author-email: benoit@marmelune.net
License: BSD
Keywords: shell path subprocess fabric
Platform: UNKNOWN
Classifier: Development Status :: 1 - Planning
Classifier: License :: OSI Approved :: BSD License
Classifier: Intended Audience :: Developers
Classifier: Programming Language :: Python :: 2.7
